{
	"Type": "Card",
	"GUID": "5CC2663323874601BC1BE580EDD7D6DA",
	"Name": "Encounter Other World Cards",
	"CollisionType": "Regular",
	"Friction": 0.7,
	"Restitution": 0,
	"Density": 0.5,
	"SurfaceType": "Cardboard",
	"Roughness": 1,
	"Metallic": 0,
	"PrimaryColor": {
		"R": 255,
		"G": 255,
		"B": 255
	},
	"SecondaryColor": {
		"R": 0,
		"G": 0,
		"B": 0
	},
	"Flippable": true,
	"AutoStraighten": false,
	"ScriptName": "",
	"Blueprint": "",
	"Models": [],
	"Collision": [],
	"SnapPointsGlobal": false,
	"SnapPoints": [],
	"ZoomViewDirection": {
		"X": 0,
		"Y": 0,
		"Z": 0
	},
	"FrontTexture": "Encounter - Other World - front.jpg",
	"BackTexture": "Encounter - Other World - back.jpg",
	"HiddenTexture": "",
	"BackIndex": -2,
	"HiddenIndex": -1,
	"NumHorizontal": 6,
	"NumVertical": 4,
	"Width": 5.7,
	"Height": 8.89,
	"Thickness": 0.05,
	"HiddenInHand": false,
	"UsedWithCardHolders": true,
	"CanStack": true,
	"UsePrimaryColorForSide": false,
	"FrontTextureOverrideExposed": false,
	"AllowFlippedInStack": false,
	"Model": "Rounded",
	"Indices": [
		0, 1, 2, 3, 4, 5, 6, 7, 8, 9, 10, 11, 12, 13, 14, 15, 16, 17, 18, 19, 20,
		21, 22, 23
	],
	"CardNames": {}
}
