{
    "Type": "Card",
    "GUID": "448B0EDAA3D2434FA40D127FFA6C7FBA",
    "Name": "City Beneath the Sands",
    "CollisionType": "Regular",
    "Friction": 0.7,
    "Restitution": 0,
    "Density": 0.5,
    "SurfaceType": "Cardboard",
    "Roughness": 1,
    "Metallic": 0,
    "PrimaryColor": {
        "R": 255,
        "G": 255,
        "B": 255
    },
    "SecondaryColor": {
        "R": 0,
        "G": 0,
        "B": 0
    },
    "Flippable": true,
    "Blueprint": "",
    "Models": [],
    "Collision": [],
    "SnapPoints": [],
    "FrontTexture": "QvSWrTW.jpg",
    "BackTexture": "n35wZSl.png",
    "BackIndex": -2,
    "NumHorizontal": 10,
    "NumVertical": 7,
    "Width": 7.7241901809657145,
    "Height": 12.105074164200001,
    "Thickness": 0.05,
    "HiddenInHand": true,
    "CanStack": true,
    "UsedWithCardHolders": true,
    "Model": "StaticMesh'/Game/Meshes/Cards/SquareRounded.SquareRounded'",
    "Indices": [
        0,
        1,
        2,
        3,
        4,
        5,
        6,
        7
    ],
    "ConvexCollision": true,
    "ShapeAccuracy": 10
}