{
	"Type": "Card",
	"GUID": "68911FDF43E1C5334590C1ADF8FE7AEA",
	"Name": "Assets",
	"Metadata": "",
	"CollisionType": "Regular",
	"Friction": 0.7,
	"Restitution": 0,
	"Density": 0.5,
	"SurfaceType": "Cardboard",
	"Roughness": 1,
	"Metallic": 0,
	"PrimaryColor":
	{
		"R": 255,
		"G": 255,
		"B": 255
	},
	"SecondaryColor":
	{
		"R": 0,
		"G": 0,
		"B": 0
	},
	"Flippable": true,
	"AutoStraighten": false,
	"ShouldSnap": true,
	"ScriptName": "",
	"Blueprint": "",
	"Models": [],
	"Collision": [],
	"SnapPointsGlobal": false,
	"SnapPoints": [],
	"ZoomViewDirection":
	{
		"X": 0,
		"Y": 0,
		"Z": 0
	},
	"FrontTexture": "02 Forsaken Lore/assets - front.jpg",
	"BackTexture": "Asset - back.jpg",
	"HiddenTexture": "",
	"BackIndex": -2,
	"HiddenIndex": -1,
	"NumHorizontal": 4,
	"NumVertical": 4,
	"Width": 4,
	"Height": 6.3,
	"Thickness": 0.05,
	"HiddenInHand": false,
	"UsedWithCardHolders": true,
	"CanStack": true,
	"UsePrimaryColorForSide": false,
	"FrontTextureOverrideExposed": false,
	"AllowFlippedInStack": false,
	"MirrorBack": true,
	"Model": "Rounded",
	"Indices": [ 0, 1, 2, 3, 4, 5, 6, 7, 8, 9, 10, 11, 12, 13, 14, 15 ],
	"CardNames":
	{
		"0": ".45 Colt Revolver",
		"1": "Appeal to the Council",
		"2": "Bodyguard",
		"3": "Conspiracy Theorist",
		"4": "Elder Sign",
		"5": "Enchanted Blade",
		"6": "Fresh Fruit",
		"7": "Intelligence Report",
		"8": "Lantern",
		"9": "Lucky Ring",
		"10": "Mystic Bounty Hunter",
		"11": "Police Assistance",
		"12": "Police Ledger",
		"13": "Research student",
		"14": "Syndicate Agent",
		"15": "Tear Gas"
	},
	"CardMetadata":
	{
		"0": "[\"Item\", \"Weapon\"]",
		"1": "[\"Service\"]",
		"2": "[\"Ally\"]",
		"3": "[\"Ally\"]",
		"4": "[\"Trinket\", \"Magical\"]",
		"5": "[\"Trinket\", \"Magical\", \"Weapon\"]",
		"6": "[\"Item\"]",
		"7": "[\"Service\"]",
		"8": "[\"Item\"]",
		"9": "[\"Trinket\"]",
		"10": "[\"Ally\"]",
		"11": "[\"Service\"]",
		"12": "[\"Item\"]",
		"13": "[\"Ally\"]",
		"14": "[\"Ally\"]",
		"15": "[\"Item\", \"Weapon\"]"
	}
}