{
    "Type": "Card",
    "GUID": "B29215F5812443EEB4FC13178FBBF93A",
    "Name": "Pursuits",
    "CollisionType": "Regular",
    "Friction": 0.7,
    "Restitution": 0,
    "Density": 0.5,
    "SurfaceType": "Cardboard",
    "Roughness": 1,
    "Metallic": 0,
    "PrimaryColor": {
        "R": 255,
        "G": 255,
        "B": 255
    },
    "SecondaryColor": {
        "R": 0,
        "G": 0,
        "B": 0
    },
    "Flippable": true,
    "Blueprint": "",
    "Models": [],
    "Collision": [],
    "SnapPoints": [],
    "FrontTexture": "O68wVej.jpg",
    "BackTexture": "TdJlHX3.jpg",
    "BackIndex": -3,
    "NumHorizontal": 8,
    "NumVertical": 6,
    "Width": 7.1882157762229,
    "Height": 11.072696218799999,
    "Thickness": 0.05,
    "HiddenInHand": true,
    "CanStack": true,
    "UsedWithCardHolders": true,
    "Model": "StaticMesh'/Game/Meshes/Cards/SquareRounded.SquareRounded'",
    "Indices": [
        21,
        23,
        22,
        20
    ],
    "ConvexCollision": true,
    "ShapeAccuracy": 10
}