{
    "Type": "Generic",
    "GUID": "D19EA7B69EDA437983D4C503FB1F3714",
    "Name": "The Sand Bat",
    "CollisionType": "Regular",
    "Friction": 0.7,
    "Restitution": 0.3,
    "Density": 1,
    "SurfaceType": "Plastic",
    "Roughness": 0.8,
    "Metallic": 0,
    "PrimaryColor": {
        "R": 254,
        "G": 253,
        "B": 254
    },
    "SecondaryColor": {
        "R": 0,
        "G": 0,
        "B": 0
    },
    "Flippable": false,
    "Blueprint": "",
    "Models": [
        {
            "Model": "82D6619F4B6058DD76BEEDD8D9431D19BB80114D_aaaa.obj",
            "Offset": {
                "X": 0,
                "Y": 0,
                "Z": 0
            },
            "Scale": {
                "X": 3.81,
                "Y": 3.81,
                "Z": 3.81
            },
            "Rotation": {
                "X": 0,
                "Y": 0,
                "Z": 0
            },
            "Texture": "5rgT11N.jpg",
            "IsTransparent": false,
            "UseOverrides": true,
            "SurfaceType": "Plastic"
        }
    ],
    "Collision": [],
    "SnapPoints": []
}